nextstrain/cli/__init__.py
nextstrain/cli/__main__.py
nextstrain/cli/__version__.py
nextstrain/cli/argparse.py
nextstrain/cli/browser.py
nextstrain/cli/config.py
nextstrain/cli/console.py
nextstrain/cli/debug.py
nextstrain/cli/env.py
nextstrain/cli/errors.py
nextstrain/cli/gzip.py
nextstrain/cli/hostenv.py
nextstrain/cli/markdown.py
nextstrain/cli/net.py
nextstrain/cli/pathogens.py
nextstrain/cli/paths.py
nextstrain/cli/requests.py
nextstrain/cli/types.py
nextstrain/cli/url.py
nextstrain/cli/util.py
nextstrain/cli/volume.py
nextstrain/cli/authn/__init__.py
nextstrain/cli/authn/configuration.py
nextstrain/cli/authn/errors.py
nextstrain/cli/authn/session.py
nextstrain/cli/aws/__init__.py
nextstrain/cli/aws/s3.py
nextstrain/cli/aws/cognito/__init__.py
nextstrain/cli/aws/cognito/srp.py
nextstrain/cli/command/__init__.py
nextstrain/cli/command/authorization.py
nextstrain/cli/command/build.py
nextstrain/cli/command/check_setup.py
nextstrain/cli/command/debugger.py
nextstrain/cli/command/deploy.py
nextstrain/cli/command/init_shell.py
nextstrain/cli/command/login.py
nextstrain/cli/command/logout.py
nextstrain/cli/command/run.py
nextstrain/cli/command/setup.py
nextstrain/cli/command/shell.py
nextstrain/cli/command/update.py
nextstrain/cli/command/version.py
nextstrain/cli/command/view.py
nextstrain/cli/command/whoami.py
nextstrain/cli/command/remote/__init__.py
nextstrain/cli/command/remote/delete.py
nextstrain/cli/command/remote/download.py
nextstrain/cli/command/remote/ls.py
nextstrain/cli/command/remote/upload.py
nextstrain/cli/remote/__init__.py
nextstrain/cli/remote/nextstrain_dot_org.py
nextstrain/cli/remote/s3.py
nextstrain/cli/resources/__init__.py
nextstrain/cli/resources/bashrc
nextstrain/cli/resources/schema-pathogen-v0.json
nextstrain/cli/rst/__init__.py
nextstrain/cli/rst/sphinx.py
nextstrain/cli/runner/__init__.py
nextstrain/cli/runner/ambient.py
nextstrain/cli/runner/conda.py
nextstrain/cli/runner/docker.py
nextstrain/cli/runner/singularity.py
nextstrain_cli-10.4.2.dist-info/licenses/LICENSE
nextstrain_cli-10.4.2.dist-info/licenses/LICENSE.cognito-srp
nextstrain_cli-10.4.2.dist-info/licenses/LICENSE.id3c
nextstrain_cli-10.4.2.dist-info/licenses/LICENSE.sphinx
nextstrain_cli-10.4.2.dist-info/METADATA
nextstrain_cli-10.4.2.dist-info/WHEEL
nextstrain_cli-10.4.2.dist-info/entry_points.txt
nextstrain_cli-10.4.2.dist-info/top_level.txt
nextstrain_cli-10.4.2.dist-info/RECORD
